paramiko_cloud/__init__.py
paramiko_cloud/base.py
paramiko_cloud/grpc_server.py
paramiko_cloud/pki.py
paramiko_cloud/test_grpc_server.py
paramiko_cloud/test_helpers.py
paramiko_cloud/test_pki.py
paramiko_cloud/aws/__init__.py
paramiko_cloud/aws/keys.py
paramiko_cloud/aws/test_keys.py
paramiko_cloud/azure/__init__.py
paramiko_cloud/azure/keys.py
paramiko_cloud/azure/test_keys.py
paramiko_cloud/dummy/__init__.py
paramiko_cloud/dummy/keys.py
paramiko_cloud/dummy/test_keys.py
paramiko_cloud/gcp/__init__.py
paramiko_cloud/gcp/keys.py
paramiko_cloud/gcp/test_keys.py
paramiko_cloud/protobuf/__init__.py
paramiko_cloud/protobuf/csr_pb2.py
paramiko_cloud/protobuf/rpc_pb2.py
paramiko_cloud/protobuf/rpc_pb2_grpc.py
paramiko_cloud-1.3.0.dist-info/METADATA
paramiko_cloud-1.3.0.dist-info/WHEEL
paramiko_cloud-1.3.0.dist-info/top_level.txt
paramiko_cloud-1.3.0.dist-info/RECORD
